assistant/__init__.py
assistant/__version__.py
assistant/analyze.py
assistant/cli.py
assistant/cli_args.py
assistant/cli_interface.py
assistant/config.py
assistant/hooks_setup.py
assistant/husky_hooks_setup.py
assistant/post_commit.py
assistant/pre_commit.py
assistant/prepare_commit_msg.py
assistant/setup_db.py
commit_assistant-0.1.1.dist-info/METADATA
commit_assistant-0.1.1.dist-info/WHEEL
commit_assistant-0.1.1.dist-info/entry_points.txt
commit_assistant-0.1.1.dist-info/licenses/LICENSE
commit_assistant-0.1.1.dist-info/RECORD
