Metadata-Version: 2.4
Name: commit-assistant
Version: 0.1.1
Summary: An AI commit assistant CLI tool.
Author-email: Stone <xijieyin@gmail.com>
License-File: LICENSE
Classifier: License :: OSI Approved :: MIT License
Classifier: Operating System :: OS Independent
Classifier: Programming Language :: Python :: 3
Requires-Python: >=3.8
Requires-Dist: google-genai
Requires-Dist: rich
